setup.py
gaussian_and_binomial_distributions_probability/Binomialdistribution.py
gaussian_and_binomial_distributions_probability/Gaussiandistribution.py
gaussian_and_binomial_distributions_probability/Generaldistribution.py
gaussian_and_binomial_distributions_probability/__init__.py
gaussian_and_binomial_distributions_probability.egg-info/PKG-INFO
gaussian_and_binomial_distributions_probability.egg-info/SOURCES.txt
gaussian_and_binomial_distributions_probability.egg-info/dependency_links.txt
gaussian_and_binomial_distributions_probability.egg-info/not-zip-safe
gaussian_and_binomial_distributions_probability.egg-info/top_level.txt