Metadata-Version: 1.0
Name: gaussian-and-binomial-distributions-probability
Version: 0.1
Summary: Gaussian and Binomial distributions
Home-page: UNKNOWN
Author: Aman Makhija
Author-email: amanmakhija2205@gmail.com
License: UNKNOWN
Platform: UNKNOWN
